numerospremiers/numerospremiers.py
numerospremiers-1.0.dist-info/LICENSE
numerospremiers-1.0.dist-info/METADATA
numerospremiers-1.0.dist-info/WHEEL
numerospremiers-1.0.dist-info/top_level.txt
numerospremiers-1.0.dist-info/RECORD
