Metadata-Version: 2.1
Name: numerospremiers
Version: 1.0
Summary: A tool to know the prime numbers until the number inserted from keyboard.
Author: Maka
Author-email: macarena.coloma.06@gmail.com
License: GNU GPLv3
Keywords: primos numeros
Platform: UNKNOWN
Classifier: Development Status :: 4 - Beta
Classifier: Intended Audience :: Developers
Classifier: Topic :: Utilities
Classifier: License :: OSI Approved :: GNU General Public License v3 (GPLv3)
Classifier: Programming Language :: Python :: 3
Classifier: Operating System :: OS Independent
License-File: LICENSE
